{
   "edges":[
      {
         "source":"ads1",
         "target":"ads2",
         "info": {
           "property": {
              "bw": 1,
              "delay": 1000
           },
           "group": "",
           "view": "Data"
         }
      },
      {
         "source":"ads1",
         "target":"sur1",
         "info": {
           "property": {
              "bw": 5,
              "delay": 200
           },
           "group": "",
           "view": "Data"
         }
      },
      {
         "source":"ads2",
         "target":"sur1",
         "info": {
           "property": {
              "bw": 10,
              "delay": 100
           },
           "group": "",
           "view": "Data"
         }
      }
   ],
   "vertices":[
     {
      "info": {
        "type": "Router",
        "property": {},
        "group": [200]
      },
      "id": "ads1"
     },
     {
      "info": {
        "type": "Router",
        "property": {},
        "group": [200]
      },
      "id": "ads2"
     },
     {
      "info": {
        "type": "Router",
        "property": {},
        "group": [200]
      },
      "id": "sur1"
     }
   ],
   "graph_parameters":{
        "testbed":"MININET"
   }
}